vdsnow/__init__.py
vdsnow/__main__.py
vdsnow/audit.py
vdsnow/cli.py
vdsnow/compiler.py
vdsnow/connections.py
vdsnow/context.py
vdsnow/project_folder.py
vdsnow/snow_cli_runner.py
vdsnow/snowflake_actions.py
vdsnow/state.py
vdsnow/validation.py
vdsnow/vd_utils.py
vdsnow-0.5.3.dist-info/METADATA
vdsnow-0.5.3.dist-info/WHEEL
vdsnow-0.5.3.dist-info/entry_points.txt
vdsnow-0.5.3.dist-info/RECORD
