Metadata-Version: 2.4
Name: vdsnow
Version: 0.5.3
Summary: A CLI for Snowflake project scaffolding, execution, and validation.
Author-email: Vitor Duarte <vitordduarte95@gmail.com>
Classifier: License :: OSI Approved :: MIT License
Classifier: Operating System :: OS Independent
Classifier: Programming Language :: Python :: 3
Requires-Python: >=3.10
Requires-Dist: click>=8.1.8
Requires-Dist: pyfiglet>=1.0.3
Requires-Dist: pytest>=8.4.1
Requires-Dist: rich>=14.0.0
Requires-Dist: snowflake-cli>=3.9.1
Requires-Dist: tomli-w>=1.2.0
Requires-Dist: tomli>=2.2.1
